vocola2/README.html
vocola2/Release-2-6-notes.txt
vocola2/Release-2-7-notes.txt
vocola2/Release-2-8-notes.txt
vocola2/Release-2-9-notes.txt
vocola2/VocolaUtils.py
vocola2/__init__.py
vocola2/_vocola_main.py
vocola2/fix_example_contexts.py.txt
vocola2/natlinkvocolastartup.py
vocola2/send_input.py
vocola2/Simpscrp/ParsePlayKeysString.cpp
vocola2/Simpscrp/ParsePlayKeysString.h
vocola2/Simpscrp/PlayKeys.cpp
vocola2/Simpscrp/PlayKeys.h
vocola2/Simpscrp/SendInput.h
vocola2/Simpscrp/SendKeys.doc
vocola2/Simpscrp/StdAfx.cpp
vocola2/Simpscrp/StdAfx.h
vocola2/Simpscrp/simpscrp.cpp
vocola2/Simpscrp/simpscrp.vcproj
vocola2/Simpscrp/test.py
vocola2/exec/dvc2vcl.exe
vocola2/exec/dvc2vcl.pl
vocola2/exec/scan_extensions.py
vocola2/exec/vcl2py.py
vocola2/exec/vcl2py/__init__.py
vocola2/exec/vcl2py/ast.py
vocola2/exec/vcl2py/emit.py
vocola2/exec/vcl2py/lex.py
vocola2/exec/vcl2py/log.py
vocola2/exec/vcl2py/main.py
vocola2/exec/vcl2py/parse.py
vocola2/exec/vcl2py/transform.py
vocola2/extensions/ExtendedSendDragonKeys.py
vocola2/extensions/README.txt
vocola2/extensions/SendInput.py
vocola2/extensions/extensions.csv
vocola2/extensions/itn_d.enh
vocola2/extensions/itnoptions.ini
vocola2/extensions/vocola_ext_keys.py
vocola2/extensions/vocola_ext_pythonhelpers.py
vocola2/extensions/vocola_ext_stringqh.py
vocola2/samples/URLs.vch
vocola2/samples/_Dragon_help.vcl
vocola2/samples/_vocola.vcl
vocola2/samples/dreamweaver.vcl
vocola2/samples/emacs.vcl
vocola2/samples/explorer.vcl
vocola2/samples/files.vch
vocola2/samples/folders.vch
vocola2/samples/iexplore.vcl
vocola2/samples/keys.vch
vocola2/samples/mozilla.vcl
vocola2/samples/msdev.vcl
vocola2/samples/msedge.vcl
vocola2/samples/mstsc.vcl
vocola2/samples/natspeak.vcl
vocola2/samples/netscape.vcl
vocola2/samples/nlnotes.vcl
vocola2/samples/notepad.vcl
vocola2/samples/ntvdm.vcl
vocola2/samples/outlook.vcl
vocola2/samples/remoteControl.vch
vocola2/samples/string.vch
vocola2/samples/utilities.vch
vocola2/samples/vcledit.vcl
vocola2-3.1.9.dist-info/WHEEL
vocola2-3.1.9.dist-info/METADATA
vocola2-3.1.9.dist-info/RECORD
