Metadata-Version: 2.1
Name: vocola2
Version: 3.1.9
Summary: Vocola
Home-page: http://vocola.net/v2/
Keywords: dragon,speech,dictation,dictation-toolbox,unimacro,natlink
Author: Mark Lillibridge
Author-email: mdl@alum.mit.edu
Maintainer: Quintijn Hoogenboom
Maintainer-email: q.hoogenboom@antenna.nl
Requires-Python: >=3.8
Classifier: Development Status :: 4 - Beta
Classifier: Topic :: Multimedia :: Sound/Audio :: Speech
Classifier: Topic :: Scientific/Engineering :: Human Machine Interfaces
Requires-Dist: dtactions>=1.5.7
